dsa_downloader/__init__.py
dsa_downloader/__main__.py
dsa_downloader/asset_processor.py
dsa_downloader/cli.py
dsa_downloader/config_extractor.py
dsa_downloader/gamedata_downloader.py
dsa_downloader/language_downloader.py
dsa_downloader/meta.py
dsa_downloader/meta_pb2.py
dsa_downloader/metadata.py
dsa_downloader-0.0.8.dist-info/LICENSE
dsa_downloader-0.0.8.dist-info/METADATA
dsa_downloader-0.0.8.dist-info/WHEEL
dsa_downloader-0.0.8.dist-info/entry_points.txt
dsa_downloader-0.0.8.dist-info/top_level.txt
dsa_downloader-0.0.8.dist-info/RECORD
